gvcode/__init__.py
gvcode/gvcode.py
gvcode/fonts/arial.ttf
gvcode/fonts/calibri.ttf
gvcode/fonts/simsun.ttc
gvcode-1.0.3.dist-info/LICENSE
gvcode-1.0.3.dist-info/METADATA
gvcode-1.0.3.dist-info/WHEEL
gvcode-1.0.3.dist-info/top_level.txt
gvcode-1.0.3.dist-info/RECORD
