Metadata-Version: 2.1
Name: gvcode
Version: 1.0.3
Summary: A useful verification code generation tool.
Home-page: https://github.com/miloira/gvcode
Author: Msky
Author-email: 690126048@qq.com
License: GNU
Platform: UNKNOWN
License-File: LICENSE
Requires-Dist: pillow
